src/__init__.py
src/api/README.md
src/api/__init__.py
src/api/client.py
src/api/options.py
src/api/stocks.py
src/cli/__init__.py
src/cli/main.py
src/cli/commands/__init__.py
src/cli/commands/api.py
src/cli/commands/config_cmd.py
src/cli/commands/data.py
src/cli/commands/pipeline.py
src/cli/commands/polygon.py
src/cli/commands/schema.py
src/cli/commands/validate.py
src/core/__init__.py
src/core/config_loader.py
src/core/exceptions.py
src/core/memory_monitor.py
src/core/system_profiler.py
src/download/__init__.py
src/download/async_downloader.py
src/download/bars.py
src/download/corporate_actions.py
src/download/corporate_actions_optimized.py
src/download/crypto.py
src/download/delisted_stocks.py
src/download/economy.py
src/download/financial_ratios_downloader.py
src/download/forex.py
src/download/fundamentals.py
src/download/indicators.py
src/download/indices.py
src/download/market_status.py
src/download/news.py
src/download/options.py
src/download/polygon_rest_client.py
src/download/reference_data.py
src/download/s3_catalog.py
src/download/snapshots.py
src/download/sync_downloader.py
src/download/trades_quotes.py
src/features/__init__.py
src/features/definitions.py
src/features/definitions_simple.py
src/features/definitions_simple_minute.py
src/features/feature_engineer.py
src/features/financial_ratios.py
src/features/options_parser.py
src/ingest/__init__.py
src/ingest/base_ingestor.py
src/ingest/polars_ingestor.py
src/ingest/streaming_ingestor.py
src/maintenance/README.md
src/maintenance/__init__.py
src/maintenance/data_integrity_checker.py
src/orchestration/__init__.py
src/orchestration/ingestion_orchestrator.py
src/query/__init__.py
src/query/query_cache.py
src/query/query_engine.py
src/storage/__init__.py
src/storage/metadata_manager.py
src/storage/parquet_manager.py
src/storage/schemas.py
src/transform/__init__.py
src/transform/qlib_binary_validator.py
src/transform/qlib_binary_writer.py
src/utils/__init__.py
src/utils/data_loader.py
quantmini-0.2.0.dist-info/METADATA
quantmini-0.2.0.dist-info/WHEEL
quantmini-0.2.0.dist-info/entry_points.txt
quantmini-0.2.0.dist-info/licenses/LICENSE
quantmini-0.2.0.dist-info/RECORD
