Metadata-Version: 2.4
Name: quantmini
Version: 0.2.0
Summary: High-Performance Medallion Architecture Data Pipeline for Financial Market Data with Qlib Integration
Project-URL: Homepage, https://github.com/nittygritty-zzy/quantmini
Project-URL: Documentation, https://quantmini.readthedocs.io
Project-URL: Repository, https://github.com/nittygritty-zzy/quantmini
Project-URL: Issues, https://github.com/nittygritty-zzy/quantmini/issues
Project-URL: Changelog, https://github.com/nittygritty-zzy/quantmini/blob/main/docs/changelog/README.md
Author-email: Zheyuan Zhao <zheyuan28@gmail.com>
Maintainer-email: Zheyuan Zhao <zheyuan28@gmail.com>
License: MIT
License-File: LICENSE
Keywords: algorithmic-trading,alpha-factors,data-pipeline,machine-learning,polygon-io,qlib,quantitative-finance,trading
Classifier: Development Status :: 3 - Alpha
Classifier: Intended Audience :: Developers
Classifier: Intended Audience :: Financial and Insurance Industry
Classifier: Intended Audience :: Science/Research
Classifier: License :: OSI Approved :: MIT License
Classifier: Programming Language :: Python :: 3
Classifier: Programming Language :: Python :: 3.10
Classifier: Programming Language :: Python :: 3.11
Classifier: Programming Language :: Python :: 3.12
Classifier: Topic :: Office/Business :: Financial :: Investment
Classifier: Topic :: Scientific/Engineering :: Artificial Intelligence
Requires-Python: >=3.10
Requires-Dist: aioboto3>=13.0.1
Requires-Dist: aiofiles>=24.1.0
Requires-Dist: boto3>=1.35.74
Requires-Dist: click>=8.1.0
Requires-Dist: duckdb>=1.0.0
Requires-Dist: httpx[http2]>=0.27.0
Requires-Dist: pandas-market-calendars>=4.0.0
Requires-Dist: pandas>=2.2.3
Requires-Dist: polars>=1.18.0
Requires-Dist: polygon-api-client>=1.14.0
Requires-Dist: psutil>=6.1.1
Requires-Dist: pyarrow>=18.1.0
Requires-Dist: pyqlib>=0.9.0
Requires-Dist: pyyaml>=6.0.2
Requires-Dist: requests>=2.31.0
Provides-Extra: all
Requires-Dist: catboost>=1.2.7; extra == 'all'
Requires-Dist: gymnasium>=1.0.0; extra == 'all'
Requires-Dist: lightgbm>=4.5.0; extra == 'all'
Requires-Dist: myst-parser>=2.0.0; extra == 'all'
Requires-Dist: pytest-asyncio>=0.25.2; extra == 'all'
Requires-Dist: pytest-cov>=6.0.0; extra == 'all'
Requires-Dist: pytest>=8.3.4; extra == 'all'
Requires-Dist: scikit-learn>=1.5.0; extra == 'all'
Requires-Dist: sphinx-autodoc-typehints>=1.25.0; extra == 'all'
Requires-Dist: sphinx-rtd-theme>=2.0.0; extra == 'all'
Requires-Dist: sphinx>=7.0.0; extra == 'all'
Requires-Dist: xgboost>=2.1.0; extra == 'all'
Provides-Extra: dev
Requires-Dist: pytest-asyncio>=0.25.2; extra == 'dev'
Requires-Dist: pytest-cov>=6.0.0; extra == 'dev'
Requires-Dist: pytest>=8.3.4; extra == 'dev'
Provides-Extra: docs
Requires-Dist: myst-parser>=2.0.0; extra == 'docs'
Requires-Dist: sphinx-autodoc-typehints>=1.25.0; extra == 'docs'
Requires-Dist: sphinx-rtd-theme>=2.0.0; extra == 'docs'
Requires-Dist: sphinx>=7.0.0; extra == 'docs'
Provides-Extra: ml
Requires-Dist: catboost>=1.2.7; extra == 'ml'
Requires-Dist: gymnasium>=1.0.0; extra == 'ml'
Requires-Dist: lightgbm>=4.5.0; extra == 'ml'
Requires-Dist: scikit-learn>=1.5.0; extra == 'ml'
Requires-Dist: xgboost>=2.1.0; extra == 'ml'
